mmtf/__init__.py
mmtf/api/__init__.py
mmtf/api/default_api.py
mmtf/api/mmtf_reader.py
mmtf/api/mmtf_writer.py
mmtf/codecs/__init__.py
mmtf/codecs/codecs.py
mmtf/codecs/default_codec.py
mmtf/codecs/decoders/__init__.py
mmtf/codecs/decoders/decoders.py
mmtf/codecs/decoders/numpy_decoders.py
mmtf/codecs/encoders/__init__.py
mmtf/codecs/encoders/encoders.py
mmtf/converters/__init__.py
mmtf/converters/converters.py
mmtf/converters/numpy_converters.py
mmtf/tests/__init__.py
mmtf/tests/codec_tests.py
mmtf/utils/__init__.py
mmtf/utils/codec_utils.py
mmtf/utils/constants.py
mmtf/utils/decoder_utils.py
mmtf_python-1.1.3.dist-info/LICENSE.txt
mmtf_python-1.1.3.dist-info/METADATA
mmtf_python-1.1.3.dist-info/WHEEL
mmtf_python-1.1.3.dist-info/top_level.txt
mmtf_python-1.1.3.dist-info/RECORD
